{
  "label_text_app_subtitle": "crwdns27406:0crwdne27406:0",
  "label_button_facebook": "crwdns27407:0crwdne27407:0",
  "label_button_google": "crwdns27408:0crwdne27408:0",
  "label_button_try_app": "crwdns27409:0crwdne27409:0",
  "label_button_acknowledge": "crwdns27410:0crwdne27410:0",
  "label_button_cancel": "crwdns27411:0crwdne27411:0",
  "label_button_continue": "crwdns27412:0crwdne27412:0",
  "label_trash_status_threat": "crwdns27413:0crwdne27413:0",
  "label_trash_status_regular": "crwdns27414:0crwdne27414:0",
  "label_trash_status_cleaned": "crwdns27415:0crwdne27415:0",
  "label_trash_status_outdated": "crwdns27416:0crwdne27416:0",
  "label_trash_status_user": "crwdns27417:0crwdne27417:0",
  "label_trash_status_change_location": "crwdns27418:0crwdne27418:0",
  "label_trash_status_state_threat": "crwdns27419:0crwdne27419:0",
  "label_trash_status_state_regular": "crwdns27420:0crwdne27420:0",
  "label_trash_status_state_cleaned": "crwdns27421:0crwdne27421:0",
  "label_trash_status_state_outdated": "crwdns27422:0crwdne27422:0",
  "label_TP_created_date": "crwdns27423:0crwdne27423:0",
  "label_TP_updated_date": "crwdns27424:0crwdne27424:0",
  "label_TP_by": "crwdns27425:0crwdne27425:0",
  "label_trash_amount_handful": "crwdns27426:0crwdne27426:0",
  "label_trash_amount_bagful": "crwdns27427:0crwdne27427:0",
  "label_trash_amount_cartloadl": "crwdns27428:0crwdne27428:0",
  "label_trash_amount_truckload": "crwdns27429:0crwdne27429:0",
  "label_trash_type_plastic": "crwdns27430:0crwdne27430:0",
  "label_trash_type_metal": "crwdns27431:0crwdne27431:0",
  "label_trash_type_glass": "crwdns27432:0crwdne27432:0",
  "label_trash_type_electro": "crwdns27433:0crwdne27433:0",
  "label_trash_type_paper": "crwdns27434:0crwdne27434:0",
  "label_trash_type_tyres": "crwdns27435:0crwdne27435:0",
  "label_trash_type_dom_waste": "crwdns27436:0crwdne27436:0",
  "label_trash_type_furniture": "crwdns27437:0crwdne27437:0",
  "label_trash_type_org_waste": "crwdns27438:0crwdne27438:0",
  "label_header_tc": "crwdns27439:0crwdne27439:0",
  "label_button_tc_agree": "crwdns27440:0crwdne27440:0",
  "label_header_map": "crwdns27441:0crwdne27441:0",
  "label_text_popover_subtitle": "crwdns27442:0crwdne27442:0",
  "label_text_popover_text": "crwdns27443:0crwdne27443:0",
  "label_header_activity": "crwdns27444:0crwdne27444:0",
  "label_text_activity_empty_subtitle": "crwdns27445:0crwdne27445:0",
  "label_text_activity_empty_text": "crwdns27446:0crwdne27446:0",
  "label_text_activity_empty_hint": "crwdns27447:0crwdne27447:0",
  "label_header_notific": "crwdns27448:0crwdne27448:0",
  "label_text_notific_empty_subtitle": "crwdns27449:0crwdne27449:0",
  "label_text_notific_empty_text": "crwdns27450:0crwdne27450:0",
  "label_header_profile": "crwdns27451:0crwdne27451:0",
  "label_header_settings": "crwdns27452:0crwdne27452:0",
  "label_button_country_empty": "crwdns27453:0crwdne27453:0",
  "label_text_country": "crwdns27454:0crwdne27454:0",
  "label_header_select_country": "crwdns27455:0crwdne27455:0",
  "label_text_select_country_hint": "crwdns27456:0crwdne27456:0",
  "label_button_tc": "crwdns27457:0crwdne27457:0",
  "label_button_logout": "crwdns27458:0crwdne27458:0",
  "label_text_congrats_image": "crwdns27459:0crwdne27459:0",
  "label_text_congrats_subtitle": "crwdns27460:0crwdne27460:0",
  "label_text_congrats_text": "crwdns27461:0crwdne27461:0",
  "label_header_createTP": "crwdns27462:0crwdne27462:0",
  "label_button_createTP_editloc": "crwdns27463:0crwdne27463:0",
  "label_header_edit_loc": "crwdns27464:0crwdne27464:0",
  "label_button_edit_loc_set": "crwdns27465:0crwdne27465:0",
  "label_text_createTP_status_subtitle": "crwdns27466:0crwdne27466:0",
  "label_text_createTP_status_text": "crwdns27467:0crwdne27467:0",
  "label_text_createTP_add_photos": "crwdns27468:0crwdne27468:0",
  "label_text_createTP_select_amount": "crwdns27469:0crwdne27469:0",
  "label_text_createTP_select_type": "crwdns27470:0crwdne27470:0",
  "label_text_createTP_add_hashtags": "crwdns27471:0crwdne27471:0",
  "label_text_createTP_add_hashtags_hint": "crwdns27472:0crwdne27472:0",
  "label_button_createTP_confirm_create": "crwdns27473:0crwdne27473:0",
  "label_alert_createTP_success": "crwdns27474:0crwdne27474:0",
  "label_text_detailsTP_photos": "crwdns27475:0crwdne27475:0",
  "label_text_detailsTP_amount": "crwdns27476:0crwdne27476:0",
  "label_text_detailsTP_type": "crwdns27477:0crwdne27477:0",
  "label_text_editTP_ask": "crwdns27478:0crwdne27478:0",
  "label_text_editTP_letsconfirm": "crwdns27479:0crwdne27479:0",
  "label_alert_editTP_confirm": "crwdns27480:0crwdne27480:0",
  "label_text_editTP_letsedit": "crwdns27481:0crwdne27481:0",
  "label_header_editTP": "crwdns27482:0crwdne27482:0",
  "label_button_editTP_save": "crwdns27483:0crwdne27483:0",
  "label_alert_editTP_edit": "crwdns27484:0crwdne27484:0",
  "label_alert_editTP_delete": "crwdns27485:0crwdne27485:0",
  "label_error_editTP_out_of_rng_subtitle": "crwdns27486:0crwdne27486:0",
  "label_error_editTP_out_of_rng_text": "crwdns27487:0crwdne27487:0",
  "label_error_saveTP_subtitle": "crwdns27488:0crwdne27488:0",
  "label_error_saveTP_pic_and_type": "crwdns27489:0crwdne27489:0",
  "label_error_saveTP_picture": "crwdns27490:0crwdne27490:0",
  "label_error_saveTP_trash_type": "crwdns27491:0crwdne27491:0",
  "label_error_change_loc_subtitle": "crwdns27492:0crwdne27492:0",
  "label_error_change_loc_text": "crwdns27493:0crwdne27493:0",
  "label_error_generic_error_subtitle": "crwdns27494:0crwdne27494:0",
  "label_error_generic_error_text": "crwdns27495:0crwdne27495:0",
  "label_error_network_subtitle": "crwdns27496:0crwdne27496:0",
  "label_error_network_text": "crwdns27497:0crwdne27497:0",
  "label_error_location_subtitle": "crwdns27498:0crwdne27498:0",
  "label_error_location_text": "crwdns27499:0crwdne27499:0",
  "label_error_loc_permission_text": "crwdns27500:0crwdne27500:0",
  "label_trash_details_header": "crwdns27501:0crwdne27501:0",
  "label_privacy_policy_header": "crwdns27502:0crwdne27502:0",
  "label_about_header": "crwdns27503:0crwdne27503:0",
  "label_edit_trashpoint_button": "crwdns27504:0crwdne27504:0",
  "label_100m_limit_modal": "crwdns27505:0crwdne27505:0",
  "label_retry_button": "crwdns27506:0crwdne27506:0",
  "label_country_picker_placeholder": "crwdns27507:0crwdne27507:0",
  "label_camera_permission_warning_ios": "crwdns27508:0crwdne27508:0",
  "label_camera_permission_warning_android": "crwdns27509:0crwdne27509:0",
  "label_camera_error_title": "crwdns27510:0crwdne27510:0",
  "label_error_modal_default_title": "crwdns27511:0crwdne27511:0",
  "label_error_modal_default_subtitle": "crwdns27512:0crwdne27512:0",
  "label_location_permission_warning_ios": "crwdns27513:0crwdne27513:0",
  "label_location_permission_warning_android": "crwdns27514:0crwdne27514:0",
  "label_location_off_warning": "crwdns27515:0crwdne27515:0",
  "label_location_modal_title": "crwdns27516:0crwdne27516:0",
  "label_network_off_warning_title": "crwdns27517:0crwdne27517:0",
  "label_network_off_warning": "crwdns27518:0crwdne27518:0",
  "label_loading_image_text": "crwdns27519:0crwdne27519:0",
  "label_loading_image_subtext": "crwdns27520:0crwdne27520:0",
  "label_create_marker_missing_photos": "crwdns27521:0crwdne27521:0",
  "label_edit_marker_missing_photos": "crwdns27522:0crwdne27522:0",
  "label_confirm_marker_missing_photos": "crwdns27523:0crwdne27523:0",
  "label_button_delete": "crwdns27524:0crwdne27524:0",
  "label_delete_photo_title": "crwdns27525:0crwdne27525:0",
  "label_delete_photo_subtitle": "crwdns27526:0crwdne27526:0",
  "label_text_about_1": "crwdns27527:0crwdne27527:0",
  "label_text_about_2": "crwdns27528:0crwdne27528:0",
  "label_text_about_3": "crwdns27529:0crwdne27529:0",
  "label_text_about_4": "crwdns27530:0crwdne27530:0",
  "label_text_about_5": "crwdns27531:0crwdne27531:0",
  "label_button_editTP_delete": "crwdns27532:0crwdne27532:0",
  "label_locked_account_warning": "crwdns27533:0crwdne27533:0"
}